<data><numberOfRecords>7820</numberOfRecords><numberOfReturn>20</numberOfReturn><startRecord>7801</startRecord><records><record><recordData><speechRecord><speechID>112804573X01619931112_723</speechID><issueID>112804573X01619931112</issueID><imageKind>会議録</imageKind><searchObject>723</searchObject><session>128</session><nameOfHouse>衆議院</nameOfHouse><nameOfMeeting>政治改革に関する調査特別委員会</nameOfMeeting><issue>第16号</issue><date>1993-11-12</date><closing></closing><speechOrder>723</speechOrder><speaker>茂木敏充</speaker><speakerYomi>もてぎとしみつ</speakerYomi><speakerGroup>さきがけ・日本新党</speakerGroup><speakerPosition></speakerPosition><speakerRole></speakerRole><speech>○茂木委員　さきがけ日本新党の茂木敏充でございます。
　本日は、意見陳述者の皆さん、本当に大変貴重な御意見ありがとうございます。私も、左近座長のもとの派遣委員の一人といたしまして、皆さんからいただきました貴重な御意見を地方の確かな声として国会に持ち帰りますことを、まずもってお約束申し上げたいと思います。
　いろいろ伺いたいことはありますが、時間の関係がございますので、もし座長の方からお許しがいただけましたら、最初の二問については、大変失礼なのですが、賛成か反対か、挙手で皆さんにお答えいただければと思っております。</speech><startPage>179</startPage><speechURL>https://kokkai.ndl.go.jp/txt/112804573X01619931112/723</speechURL><meetingURL>https://kokkai.ndl.go.jp/txt/112804573X01619931112</meetingURL><pdfURL>https://kokkai.ndl.go.jp/img/112804573X01619931112/179</pdfURL></speechRecord></recordData></record><record><recordData><speechRecord><speechID>112804573X01619931112_725</speechID><issueID>112804573X01619931112</issueID><imageKind>会議録</imageKind><searchObject>725</searchObject><session>128</session><nameOfHouse>衆議院</nameOfHouse><nameOfMeeting>政治改革に関する調査特別委員会</nameOfMeeting><issue>第16号</issue><date>1993-11-12</date><closing></closing><speechOrder>725</speechOrder><speaker>茂木敏充</speaker><speakerYomi>もてぎとしみつ</speakerYomi><speakerGroup>さきがけ・日本新党</speakerGroup><speakerPosition></speakerPosition><speakerRole></speakerRole><speech>○茂木委員　はい。それではお聞きすることにします。
　まず、きょう三人の方が現職の議員でいらっしゃる。それから、三人の方は議員でいらっしゃらない。こういうことで、まず議員の三人の方に、個別の問題ですがお聞きしたいと思うのですが、政治というのは理念だけではなくて現実のものである、そういうことを認識しておるつもりでございます。
　そこで、県会議員の方、そして市会議員の方、地方議員をおやりになる上で、企業献金なしではやはりやっていけないのか。もしお差し支えがなかったら、やっていけないとするのなら、特にどんな分野にお金がかかってしまうのか。議会活動なのか、それとも日常の政治活動なのか、それから特定の、選挙のときの選挙費用なのか、これをお伺いしたいと思います。
　それから、献金のあり方でございますが、地方におきましては、やはり中小企業のオーナーさんといいますか、社長さんが御自分の判断で企業献金をされる、こういうケースが多いかと思うのです。そういう方が何の見返りもなしに、いわゆる立派な方で献金されている、こういうケースが多いと思うのですが、三千円、五千円、一万円、こういった献金の場合、まあこれは五十万円、百万円ということだと別だと思うのですが、企業からではなくても、そのオーナーさんが個人として献金していただける、こんなことも私は考えられるのじゃないかと思うのですが、いかがでしょうか。</speech><startPage>179</startPage><speechURL>https://kokkai.ndl.go.jp/txt/112804573X01619931112/725</speechURL><meetingURL>https://kokkai.ndl.go.jp/txt/112804573X01619931112</meetingURL><pdfURL>https://kokkai.ndl.go.jp/img/112804573X01619931112/179</pdfURL></speechRecord></recordData></record><record><recordData><speechRecord><speechID>112804573X01619931112_735</speechID><issueID>112804573X01619931112</issueID><imageKind>会議録</imageKind><searchObject>735</searchObject><session>128</session><nameOfHouse>衆議院</nameOfHouse><nameOfMeeting>政治改革に関する調査特別委員会</nameOfMeeting><issue>第16号</issue><date>1993-11-12</date><closing></closing><speechOrder>735</speechOrder><speaker>茂木敏充</speaker><speakerYomi>もてぎとしみつ</speakerYomi><speakerGroup>さきがけ・日本新党</speakerGroup><speakerPosition></speakerPosition><speakerRole></speakerRole><speech>○茂木委員　今の質問に関連しまして、私の趣旨がしっかり伝わらなかったのかもしれませんが、久保田意見陳述人の方ですが、私は、決して見返りを求めているということを申し上げたのではなくて、何の見返りも求めない方が多いのではないか。その上で、企業献金を個人献金に振りかえられないものか、このような趣旨から御質問させていただきましたので、誤解のないようにお願いいたします。
　それから、中村陳述人には、私は国会へぜひ皆さんの声を持ち帰りたい、このような冒頭のごあいさつをさせていただいておりますので、その点はぜひ趣旨を御理解いただきたいと思います。
　続きまして、今度は議員でない方にお伺いしたいのですが、今地方議員の声をお伺いしてわかったわけですが、今度は我々国会議員の役割が今後どうあるべきか、このことをお三人の方に伺いたいと思うのです。
　これまでは確かに、国会議員といいましてもそれぞれの地域代表であって、公共事業を持ってくる、特定の利益誘導をする、こういう時代であったかもしれませんが、世界史が大きく変わるこういう時代にあって、本当に国会議員という役割がだんだん全国的な視野で、外交、防衛問題に始まり、教育、福祉、そして地方分権、規制緩和、地方が求めている全体の声というのを国会の場で具現していく、これが本来の意味での国会議員の役割になってきているのではないかなと思います。そうなってきますと、単に地方の声というのを、地元選出の国会議員が何人いるか、こういうことだけではかるのはおかしいような時代になってきているような気がするのですが、その点、いかがでしょうか。</speech><startPage>179</startPage><speechURL>https://kokkai.ndl.go.jp/txt/112804573X01619931112/735</speechURL><meetingURL>https://kokkai.ndl.go.jp/txt/112804573X01619931112</meetingURL><pdfURL>https://kokkai.ndl.go.jp/img/112804573X01619931112/179</pdfURL></speechRecord></recordData></record><record><recordData><speechRecord><speechID>112804573X01619931112_739</speechID><issueID>112804573X01619931112</issueID><imageKind>会議録</imageKind><searchObject>739</searchObject><session>128</session><nameOfHouse>衆議院</nameOfHouse><nameOfMeeting>政治改革に関する調査特別委員会</nameOfMeeting><issue>第16号</issue><date>1993-11-12</date><closing></closing><speechOrder>739</speechOrder><speaker>茂木敏充</speaker><speakerYomi>もてぎとしみつ</speakerYomi><speakerGroup>さきがけ・日本新党</speakerGroup><speakerPosition></speakerPosition><speakerRole></speakerRole><speech>○茂木委員　きょうは、お話を伺いまして、皆さんがどうしても政治改革をまとめるべきだ、そういう御熱意、十分受け取らせていただいたのですが、最終的に与野党の合意案をつくるためには、どうしても細川さん、それから河野さんのトップ会談が必要になってくると思います。
　この地方公聴会の位置づけ、いろいろな考え方があるかと思いますが、この御意見を伺いながら、同時にトップ会談も進める、このことは決して私は、地方公聴会を無視しているとか軽視しているとか、そういうことにはつながらずに、どうしても政治改革をまとめるという情熱の上では、並行して進めるということもあり得るのではないか、このように考えますが、もしよろしかったら、牧野陳述者と中村陳述者に御意見をいただきたいと思います。</speech><startPage>180</startPage><speechURL>https://kokkai.ndl.go.jp/txt/112804573X01619931112/739</speechURL><meetingURL>https://kokkai.ndl.go.jp/txt/112804573X01619931112</meetingURL><pdfURL>https://kokkai.ndl.go.jp/img/112804573X01619931112/180</pdfURL></speechRecord></recordData></record><record><recordData><speechRecord><speechID>112804573X01619931112_796</speechID><issueID>112804573X01619931112</issueID><imageKind>会議録</imageKind><searchObject>796</searchObject><session>128</session><nameOfHouse>衆議院</nameOfHouse><nameOfMeeting>政治改革に関する調査特別委員会</nameOfMeeting><issue>第16号</issue><date>1993-11-12</date><closing></closing><speechOrder>796</speechOrder><speaker>茂木敏充</speaker><speakerYomi>もてぎとしみつ</speakerYomi><speakerGroup>さきがけ・日本新党</speakerGroup><speakerPosition></speakerPosition><speakerRole></speakerRole><speech>○茂木委員　日本新党の茂木敏充でございます。
　私が最後の質問をさせていただくわけですが、私のいただきました十五分が終わりますと、この国会におきます政治改革関連法案の審議時間がちょうど百十七時間になります。この百十七時間という数字は、前々回の政治改革関連法案の百七時間、その前の、大変議論を尽くしました消費税の九十六時間三十分を優に超えまして、歴代第三位の長時間審議となってまいります。第一位が昭和三十五年の日米安保、百三十六時間十三分、そして第二位が昭和四十六年の沖縄復帰特別措置法の百二十七時間十四分、これに次ぐ大変長い審議時間になりまして、その締めくくりに近いところで本当に地域の皆さんから大変貴重な御意見をいただきましたことを、まずもって心より感謝申し上げたいと思います。私も委員の一人として、皆さんからいただきました貴重な御意見を地方の確かな声として国会にしっかり持って帰りたい、このように考えております。
　今後、最終的な合意形成が与野党間で図られていくわけですが、新聞紙上なんかにもありますような、何となく足して二で割るような方向での妥協というのは私は必ずしも好ましいとは思っておりません。最終的には、これからの政治をどうしていくんだという基本方向を定めて、それに沿って与野党が歩み寄っていくということが大変重要であると思います。その基本方向についてでございますが、やはり議員だけの立場ではなくて、国民の立場からどうなのか、地域の立場からどうなのか、そういう姿勢が必要であり、その中でも、単に現状がこうだからということより、まずあるべき姿としてどうあるべきなのかというところから出発して、しかし現状があるのでそれに修正を加えよう、それが正しい修正の方向ではないかなと思っております。
　例えば選挙制度につきましても、私は将来的には選挙制度が政党・政策中心ということになってくると一票制がふさわしいのではないかなと考える部分も確かにございます。しかし今、クロスボーティングの現状が二八・七七％ございます。つまり、四人に一人以上の人がクロスボーティングを選択されている。この現状を考えると、まず二票制から出発して、将来的にクロスボーティングというのはほとんどなくなって、国民の皆さんも政党と候補者同じものを選ぶ、そうなった段階で一票制に転換していけばいいのではないか、こんなふうに考えております。
　そこで、選挙活動について幾つか議論が出ておりますが、これは戸別訪問だけではなくて、運動期間、それから選挙違反に関します規制の強化、こういった問題も含まれるわけでございます。この分野に関しましては、御意見を松室議員、山本議員からはいただきましたので、今度は服部議員、逆に今度は活動をお受けになる方の民間ということで佐藤さんに御意見をいただきたいと思うのです。
　私は、候補者や政党について国民の側が、有権者が、だれが、それからどの党が最もふさわしいかという判断材料を一番与える形というのが基本であると思っております。民主主義の原点に戻りまして、より自由というものを基本にして、ただし歯どめのルールであったりとか違反には厳しく対応する、こういう方向が重要なのではないかなと考えております。日本の有権者の政治意識というのは大変高くなってきていると私は思います。ただ、しつこく戸別訪問する、それで魅力ある政策が全く提示できない、こういう人は逆効果であって、しっかり戸別訪問してでも政策を訴えられる、理念を訴えられる、こういう候補、政党が勝っていくのではないかな。こんな意味から戸別訪問、運動期間を含めて自由度をもっと拡大することが重要ではないかなと私は思いますが、御意見いかがでしょうか。</speech><startPage>197</startPage><speechURL>https://kokkai.ndl.go.jp/txt/112804573X01619931112/796</speechURL><meetingURL>https://kokkai.ndl.go.jp/txt/112804573X01619931112</meetingURL><pdfURL>https://kokkai.ndl.go.jp/img/112804573X01619931112/197</pdfURL></speechRecord></recordData></record><record><recordData><speechRecord><speechID>112804573X01619931112_799</speechID><issueID>112804573X01619931112</issueID><imageKind>会議録</imageKind><searchObject>799</searchObject><session>128</session><nameOfHouse>衆議院</nameOfHouse><nameOfMeeting>政治改革に関する調査特別委員会</nameOfMeeting><issue>第16号</issue><date>1993-11-12</date><closing></closing><speechOrder>799</speechOrder><speaker>茂木敏充</speaker><speakerYomi>もてぎとしみつ</speakerYomi><speakerGroup>さきがけ・日本新党</speakerGroup><speakerPosition></speakerPosition><speakerRole></speakerRole><speech>○茂木委員　これからの時代、一つのキーワードというのは、国境を含めてボーダーレスになっていく、境がなくなるというのが大変大きな問題であると思います。これは単に国と国との間の国境だけではなくて、県と県の間の県境というものもだんだんなくなっていくのじゃないか。そういう時代において国会議員の役割というのはどうあるべきか。この点につきまして、こちらの奈良県は非常に大阪府とある意味でボーダーレスになりつつあるという典型的な国内のボーダーレスの例になってくると思うのです。
　そこで、もう一度服部議員と、それから大阪府の方の松室議員の方にお聞きしたいと思うのですが、国会議員の役割として、今までは確かに一つの県に、市町村に公共事業を持ってくる、悪い言葉で言ってしまいますと利益誘導、こういうことが中心であったかと思うのですが、これからの時代、やはり国会議員というものは、外交であったり、防衛、それから国の教育とか福祉の基本的な分野を決めていく、そして、全国単位で地方分権であったりとか規制緩和を進めていく、地元の問題にしましたら、もう県の問題は県会議員で、府の問題は府会議員でしっかり処理していく、それをまたがるような大きなブロックの問題等について国会議員が初めていろいろな意味で役割を発揮していく、これがあるべき姿ではないかな、このように考えております。
　そんな意味からも、これはこの選挙制度だけの問題ではないのですが、すべて県にこだわって選挙制度を考える、このことには私は多少疑問がありまして、もう少し、選挙の選び方にしましても、これからの社会、これがどうあるべきか、こういう観点が必要ではないかと考えておりますが、御意見いかがでしょうか。</speech><startPage>198</startPage><speechURL>https://kokkai.ndl.go.jp/txt/112804573X01619931112/799</speechURL><meetingURL>https://kokkai.ndl.go.jp/txt/112804573X01619931112</meetingURL><pdfURL>https://kokkai.ndl.go.jp/img/112804573X01619931112/198</pdfURL></speechRecord></recordData></record><record><recordData><speechRecord><speechID>112804573X01619931112_802</speechID><issueID>112804573X01619931112</issueID><imageKind>会議録</imageKind><searchObject>802</searchObject><session>128</session><nameOfHouse>衆議院</nameOfHouse><nameOfMeeting>政治改革に関する調査特別委員会</nameOfMeeting><issue>第16号</issue><date>1993-11-12</date><closing></closing><speechOrder>802</speechOrder><speaker>茂木敏充</speaker><speakerYomi>もてぎとしみつ</speakerYomi><speakerGroup>さきがけ・日本新党</speakerGroup><speakerPosition></speakerPosition><speakerRole></speakerRole><speech>○茂木委員　今の日本、大変大きな課題、御指摘いただきましたように、たくさん抱えております。地方分権を基本にしました行政改革、それから規制緩和を基本にしました経済改革、こういった問題を本当に一日も早く進め、二十一世紀に向けての新しい時代の基盤をつくっていかなくてはならない、このように考えております。そのためにも、まずもって今の政治改革、その土台をつくらなければいけない、こんなつもりで、皆さんからいただきました貴重な意見、しっかりと胸に受けとめさせていただきまして、最終的な詰めの作業に入らせていただきたいと思っております。
　ちょうど百十七時間、今終わろうとしております。本当に貴重な御意見、ありがとうございました。</speech><startPage>199</startPage><speechURL>https://kokkai.ndl.go.jp/txt/112804573X01619931112/802</speechURL><meetingURL>https://kokkai.ndl.go.jp/txt/112804573X01619931112</meetingURL><pdfURL>https://kokkai.ndl.go.jp/img/112804573X01619931112/199</pdfURL></speechRecord></recordData></record><record><recordData><speechRecord><speechID>112804574X00219931109_139</speechID><issueID>112804574X00219931109</issueID><imageKind>会議録</imageKind><searchObject>139</searchObject><session>128</session><nameOfHouse>衆議院</nameOfHouse><nameOfMeeting>政治改革に関する調査特別委員会公聴会</nameOfMeeting><issue>第2号</issue><date>1993-11-09</date><closing></closing><speechOrder>139</speechOrder><speaker>茂木敏充</speaker><speakerYomi>もてぎとしみつ</speakerYomi><speakerGroup>さきがけ・日本新党</speakerGroup><speakerPosition></speakerPosition><speakerRole></speakerRole><speech>○茂木委員　さきがけ日本新党の茂木敏充です。本日は、公述人の皆さんには大変貴重な御意見、ありがとうございます。
　きょうは、時間が限られておりますのでボードは使いません。そのかわり、二点に絞りまして、決断の時期と歩み寄りの方法について御意見を伺いたいと思います。
　まず、この法案の決断の時期でございますが、先月の十四日に始まりましたこの委員会での審議、既に審議時間が八十時間を超え、中央公聴会、地方公聴会での審議時間を入れますと、約百十七時間の審議時間に達する予定でございます。これは、前回の政治改革関連法案の百七時間、そしてその前の消費税関連法案の九十六時間三十分、これを優に超えまして歴代第三位、すなわち三十五年の日米安保条約、そして四十六年の沖縄復帰特別措置法に続く、歴代第三位の長時間審議となるわけです。
　確かに重要な問題ですので、十分な議論が必要だったわけですが、審議への参加者の一人といたしまして、この委員会では既にあらゆる角度からの議論が出尽くしているように私には思われます。まあごく一部には、まだ議論が足りない、こうおっしゃる方もいらっしゃるかもしれませんが、これは政治改革を片手間で聞いている一部の議員の御意見ではないかな、こんな気さえいたします。
　きょうで中央公聴会が終わりまして、あす、あさってが地方公聴会の日程というわけでございますが、その間でも今までの多くの議論を踏まえまして交渉は進められるわけですし、地方公聴会の方でよほどのハプニングがない限り、私は、今週末にもトップ会談、そして採決を含めまして決断の時期ではないかなと、このように思っておりますが、まず山岸会長にこの点について改めて、簡潔で結構ですので、御意見をいただきたいと思います。</speech><startPage>30</startPage><speechURL>https://kokkai.ndl.go.jp/txt/112804574X00219931109/139</speechURL><meetingURL>https://kokkai.ndl.go.jp/txt/112804574X00219931109</meetingURL><pdfURL>https://kokkai.ndl.go.jp/img/112804574X00219931109/30</pdfURL></speechRecord></recordData></record><record><recordData><speechRecord><speechID>112804574X00219931109_141</speechID><issueID>112804574X00219931109</issueID><imageKind>会議録</imageKind><searchObject>141</searchObject><session>128</session><nameOfHouse>衆議院</nameOfHouse><nameOfMeeting>政治改革に関する調査特別委員会公聴会</nameOfMeeting><issue>第2号</issue><date>1993-11-09</date><closing></closing><speechOrder>141</speechOrder><speaker>茂木敏充</speaker><speakerYomi>もてぎとしみつ</speakerYomi><speakerGroup>さきがけ・日本新党</speakerGroup><speakerPosition></speakerPosition><speakerRole></speakerRole><speech>○茂木委員　次に、片岡公述人に同じ質問でございますが、片岡公述人は、本年七月号の「月刊自由民主」という大変立派な月刊誌に「政治改革を延期できるか」という、大変示唆に富んだ論文を寄せておられます。また、きょうの御意見を伺いますと、私の耳には、多数決、多数決という言葉が大変耳に残っているわけでございますが、早急な決断につきまして御意見をいただきたいと思います。</speech><startPage>30</startPage><speechURL>https://kokkai.ndl.go.jp/txt/112804574X00219931109/141</speechURL><meetingURL>https://kokkai.ndl.go.jp/txt/112804574X00219931109</meetingURL><pdfURL>https://kokkai.ndl.go.jp/img/112804574X00219931109/30</pdfURL></speechRecord></recordData></record><record><recordData><speechRecord><speechID>112804574X00219931109_143</speechID><issueID>112804574X00219931109</issueID><imageKind>会議録</imageKind><searchObject>143</searchObject><session>128</session><nameOfHouse>衆議院</nameOfHouse><nameOfMeeting>政治改革に関する調査特別委員会公聴会</nameOfMeeting><issue>第2号</issue><date>1993-11-09</date><closing></closing><speechOrder>143</speechOrder><speaker>茂木敏充</speaker><speakerYomi>もてぎとしみつ</speakerYomi><speakerGroup>さきがけ・日本新党</speakerGroup><speakerPosition></speakerPosition><speakerRole></speakerRole><speech>○茂木委員　そういうことで、この法案はどうしてもつぶせない。そういうことになってきますと、次に歩み寄りの方法というのが大変重要になってくると思います。既に二十項目以上の調整項目が提案されているわけでございますが、歩み寄りの方法といたしまして、そのすべてについて足して二で割る、こういうやり方もあるかと思いますが、しかし私は、大きなくくりの分野ごとに基本方向、この法案として、政治改革としての基本方向を定めて、その基本方向に沿って政府案と自民党案の調整を行う、これが妥当な方向であろうと思っています。
　そこで、大きな分野ごとでございますが、まず議員定数及び選挙区、次に選挙活動、第三に政治資金の順で、基本方向を一括してお伺いしたいと思います。
　まず、議員定数と選挙区の問題でございますが、これは後で曽根公述人にお聞きしたいと思っておりますが、この中には、議員定数とその配分、比例区の集計単位、それから投票方式、三％条項、こういった六項目が含まれてくると思いますが、この分野に関しまして、私は、小選挙区と比例区選挙という二つの選挙を組み合わせた並立制の特徴が最大限に発揮される、このことが基本であると考えております。
　例えば、比例選挙についてもう少し詳しく申し上げますと、比例選挙の特徴が生きるという意味におきまして、比例の定数を幾つにするか、こういう問題以上に、比例区の単位と投票方式が比例選挙としてどうあるべきか、このことが重要なんではないかなと考えております。逆の言い方をしますと、比例の定数配分についてはより柔軟に対応すべきである、このようにも考えております。
　次に、選挙活動に関する分野でございますが、この点につきましては、箱崎公述人の御意見がなかったのでお聞きしたいと思っているんですが、この中には、戸別訪問、運動期間、それから選挙違反の公民権停止の強化等々五項目が含まれるわけでございますが、この選挙活動に関しましては、民主主義の原点に戻りまして、より自由を基本に、ただし違反については厳しく対応する、これが基本的な方向ではないかなと考えております。
　最後に、政治資金の問題について、山岸公述人に締めくくりにお尋ねしたいと思いますが、この中には、企業・団体献金の取り扱い、政治資金パーティーの基準、それから個人献金の税制上の優遇措置、公的助成等々十項目が含まれるわけでございますが、この政治資金の問題については、政財官の立場ではなくて国民の立場からしますと、より透明に、そしてより厳しくを基本としながら、その一方で、より幅広く集められる新たな手段を開いていく、これが今回の政治改革の基本方向ではないかな、このように考えております。
　これらをまとめまして、選挙制度については曽根公述人に、選挙活動については箱崎公述人に、そして最後に政治資金について山岸公述人に、締めくくりの御意見をいただきたいと思います。</speech><startPage>30</startPage><speechURL>https://kokkai.ndl.go.jp/txt/112804574X00219931109/143</speechURL><meetingURL>https://kokkai.ndl.go.jp/txt/112804574X00219931109</meetingURL><pdfURL>https://kokkai.ndl.go.jp/img/112804574X00219931109/30</pdfURL></speechRecord></recordData></record><record><recordData><speechRecord><speechID>112804574X00219931109_147</speechID><issueID>112804574X00219931109</issueID><imageKind>会議録</imageKind><searchObject>147</searchObject><session>128</session><nameOfHouse>衆議院</nameOfHouse><nameOfMeeting>政治改革に関する調査特別委員会公聴会</nameOfMeeting><issue>第2号</issue><date>1993-11-09</date><closing></closing><speechOrder>147</speechOrder><speaker>茂木敏充</speaker><speakerYomi>もてぎとしみつ</speakerYomi><speakerGroup>さきがけ・日本新党</speakerGroup><speakerPosition></speakerPosition><speakerRole></speakerRole><speech>○茂木委員　きょうも十分ですが、私のいただきました時間は終わりになりますので、ここで私の質問を終わりにさせていただきます。本日は、どうもありがとうございました。</speech><startPage>31</startPage><speechURL>https://kokkai.ndl.go.jp/txt/112804574X00219931109/147</speechURL><meetingURL>https://kokkai.ndl.go.jp/txt/112804574X00219931109</meetingURL><pdfURL>https://kokkai.ndl.go.jp/img/112804574X00219931109/31</pdfURL></speechRecord></recordData></record><record><recordData><speechRecord><speechID>112804573X00419931019_199</speechID><issueID>112804573X00419931019</issueID><imageKind>会議録</imageKind><searchObject>199</searchObject><session>128</session><nameOfHouse>衆議院</nameOfHouse><nameOfMeeting>政治改革に関する調査特別委員会</nameOfMeeting><issue>第4号</issue><date>1993-10-19</date><closing></closing><speechOrder>199</speechOrder><speaker>茂木敏充</speaker><speakerYomi>もてぎとしみつ</speakerYomi><speakerGroup>さきがけ・日本新党</speakerGroup><speakerPosition></speakerPosition><speakerRole></speakerRole><speech>○茂木委員　日本新党の茂木敏充です。
　私は、今回政治改革を訴えて当選させていただいた新人議員の一人といたしまして、自民党案の提出者の方にお尋ねしたいと思います。
　まず、質問に入ります前に、今回の政治改革特別委員会の開催に当たりまして、自民党の皆さんが、単に反対や審議拒否という態度ではなくて、しっかりとした対案を持って審議に臨んでいただいたことに対しまして敬意を表したいと思います。
　さて、私の質問内容でございますが、同僚の前原議員が政治資金そして腐敗防止の問題について触れさせていただきましたので、私は、選挙制度改革の問題を中心にいたしまして何点かお尋ねさせていただきたいと思っております。
　まず、今回の政治改革に関します認識でございます。
　世界の激変に対しまして、我が国内の民意も今大きく変わろうとしております。この民意の変化を小選挙区という形で集約して、また比例代表という形で反映して、的確にとらえる新しい制度づくり、これが今までの中選挙区制にかわります今回の小選挙区比例代表並立制の一つの大きな柱であると考えております。
　そこで、まず、現在の中選挙区制でしばしば問題となってきました、また昨日大島委員からも御指摘のございました一票の格差の問題につきまして、自民党案ではどのようにとらえていらっしゃるか、この基本スタンスについてお伺いしたいと思います。</speech><startPage>31</startPage><speechURL>https://kokkai.ndl.go.jp/txt/112804573X00419931019/199</speechURL><meetingURL>https://kokkai.ndl.go.jp/txt/112804573X00419931019</meetingURL><pdfURL>https://kokkai.ndl.go.jp/img/112804573X00419931019/31</pdfURL></speechRecord></recordData></record><record><recordData><speechRecord><speechID>112804573X00419931019_201</speechID><issueID>112804573X00419931019</issueID><imageKind>会議録</imageKind><searchObject>201</searchObject><session>128</session><nameOfHouse>衆議院</nameOfHouse><nameOfMeeting>政治改革に関する調査特別委員会</nameOfMeeting><issue>第4号</issue><date>1993-10-19</date><closing></closing><speechOrder>201</speechOrder><speaker>茂木敏充</speaker><speakerYomi>もてぎとしみつ</speakerYomi><speakerGroup>さきがけ・日本新党</speakerGroup><speakerPosition></speakerPosition><speakerRole></speakerRole><speech>○茂木委員　多分今のお答え、小選挙区の方に絡んだお答えであると思うのですが、自民党案によりますと比例代表の選挙も県単位ということになっております。ここに一つ私は大きな問題点があるのではないかなと思います。
　ちょっとグラフをごらんいただきたいのですが、こちらでごらんいただきますと、これは「比例代表選挙での都道府県単位の一票の格差」というものを見ております。ちょっと見にくいようでしたら、資料がございますので、委員長の御許可がいただければ皆さんにお配りしたいと思いますが。</speech><startPage>31</startPage><speechURL>https://kokkai.ndl.go.jp/txt/112804573X00419931019/201</speechURL><meetingURL>https://kokkai.ndl.go.jp/txt/112804573X00419931019</meetingURL><pdfURL>https://kokkai.ndl.go.jp/img/112804573X00419931019/31</pdfURL></speechRecord></recordData></record><record><recordData><speechRecord><speechID>112804573X00419931019_203</speechID><issueID>112804573X00419931019</issueID><imageKind>会議録</imageKind><searchObject>203</searchObject><session>128</session><nameOfHouse>衆議院</nameOfHouse><nameOfMeeting>政治改革に関する調査特別委員会</nameOfMeeting><issue>第4号</issue><date>1993-10-19</date><closing></closing><speechOrder>203</speechOrder><speaker>茂木敏充</speaker><speakerYomi>もてぎとしみつ</speakerYomi><speakerGroup>さきがけ・日本新党</speakerGroup><speakerPosition></speakerPosition><speakerRole></speakerRole><speech>○茂木委員　見ていただきますと、これは比例の方でございます。政府案ですと比例が全国単位ということで格差は出ないわけですが、例えば比例の方、県単位としますと、この比例の定数が減るのに従いまして格差が大きく広がってまいります。比例の総定数が二百五十ですと格差が一・八九、二百ですと二・四一、そして自民党案の百七十一ですと格差が二・九七。すなわち、今いわゆる憲法違反と言われております三に限りなく近い数字、このすれすれのところからスタートするわけでございます。これで本当に二十年、三十年使える新しい制度づくりと言えるのでしょうか。自民党の方にお尋ねしたいと思います。</speech><startPage>31</startPage><speechURL>https://kokkai.ndl.go.jp/txt/112804573X00419931019/203</speechURL><meetingURL>https://kokkai.ndl.go.jp/txt/112804573X00419931019</meetingURL><pdfURL>https://kokkai.ndl.go.jp/img/112804573X00419931019/31</pdfURL></speechRecord></recordData></record><record><recordData><speechRecord><speechID>112804573X00419931019_205</speechID><issueID>112804573X00419931019</issueID><imageKind>会議録</imageKind><searchObject>205</searchObject><session>128</session><nameOfHouse>衆議院</nameOfHouse><nameOfMeeting>政治改革に関する調査特別委員会</nameOfMeeting><issue>第4号</issue><date>1993-10-19</date><closing></closing><speechOrder>205</speechOrder><speaker>茂木敏充</speaker><speakerYomi>もてぎとしみつ</speakerYomi><speakerGroup>さきがけ・日本新党</speakerGroup><speakerPosition></speakerPosition><speakerRole></speakerRole><speech>○茂木委員　もう一度、二・九七という数字についてどのようにお考えか、お答えいただきたいと思います。</speech><startPage>31</startPage><speechURL>https://kokkai.ndl.go.jp/txt/112804573X00419931019/205</speechURL><meetingURL>https://kokkai.ndl.go.jp/txt/112804573X00419931019</meetingURL><pdfURL>https://kokkai.ndl.go.jp/img/112804573X00419931019/31</pdfURL></speechRecord></recordData></record><record><recordData><speechRecord><speechID>112804573X00419931019_207</speechID><issueID>112804573X00419931019</issueID><imageKind>会議録</imageKind><searchObject>207</searchObject><session>128</session><nameOfHouse>衆議院</nameOfHouse><nameOfMeeting>政治改革に関する調査特別委員会</nameOfMeeting><issue>第4号</issue><date>1993-10-19</date><closing></closing><speechOrder>207</speechOrder><speaker>茂木敏充</speaker><speakerYomi>もてぎとしみつ</speakerYomi><speakerGroup>さきがけ・日本新党</speakerGroup><speakerPosition></speakerPosition><speakerRole></speakerRole><speech>○茂木委員　ありがとうございます。
　今、一票の格差の問題について質問させていただきましたが、自民党案の比例代表の仕組みにはもう一つ大きな問題点があると思います。
　これは先週の本会議で公明党の森本議員も御指摘されました比例選での二人区、三人区の問題でございまして、私の試算によりますと、総定数が二百五十ですと、二人区、三人区が二十県なのに対しまして、何度も御指摘ありましたように百七十一の場合は何と三十四県になっていく。この結果といたしまして、先週民社党の神田議員が御指摘されましたように、大変大きな死に票が生まれてくるわけでございます。この死に票の問題につきましては、昨日自民党の石破議員も、そして本日は社会党の堀込議員も再々御指摘させていただき、御議論もあった点でございますが、こちらのグラフをごらんいただきますとさらにこの現状がよくわかってまいります。
　これは一政党にとって最大どれくらいの死に票が出るか、この割合を見たものでございますが、政府案ですと、三％条項によりまして一番出ても三％。それに対しまして自民党案ですと、県単位の比例区が定数百七十一という形で、一八・七％の死に票が生まれる可能性がございます。政府案の場合ですと、三％条項を全政党に適用いたしましても、過去二回の選挙におきまして一〇％前後の死に票でございます。しかもこの中には、諸派の方でむやみな立候補を次はやめられる、こういう方も出てくると思いますので、そうしますと五％前後それより低くなってくるのではないか。これに対しまして、自民党案は約二割、こういう数の死に票が出てくるわけでございます。
　確かに民意の集約という問題はございます。しかし、その中で、比例を導入されるという本来の意味自体がこれでは失われてしまうのではないか、このように考えておりますが、国民の、有権者の貴重な一票をこのような形で、二〇％近くもむだにされる可能性のある案についてどのようにお考えでしょうか。</speech><startPage>31</startPage><speechURL>https://kokkai.ndl.go.jp/txt/112804573X00419931019/207</speechURL><meetingURL>https://kokkai.ndl.go.jp/txt/112804573X00419931019</meetingURL><pdfURL>https://kokkai.ndl.go.jp/img/112804573X00419931019/31</pdfURL></speechRecord></recordData></record><record><recordData><speechRecord><speechID>112804573X00419931019_209</speechID><issueID>112804573X00419931019</issueID><imageKind>会議録</imageKind><searchObject>209</searchObject><session>128</session><nameOfHouse>衆議院</nameOfHouse><nameOfMeeting>政治改革に関する調査特別委員会</nameOfMeeting><issue>第4号</issue><date>1993-10-19</date><closing></closing><speechOrder>209</speechOrder><speaker>茂木敏充</speaker><speakerYomi>もてぎとしみつ</speakerYomi><speakerGroup>さきがけ・日本新党</speakerGroup><speakerPosition></speakerPosition><speakerRole></speakerRole><speech>○茂木委員　このパネルはけさまでかかって、明け方までかかってつくりまして、この棒は衆議院で五百円かけて買いましたので、もう少し明確な御答弁がいただければと、こんなふうに思うのですが、問題点は後でまとめて質問さしていただくとしまして、時間の関係もありますので、次の問題、投票方式、いわゆる一票制か二票制か、この問題に移らさしていただきたいと思います。
　政党中心の選挙、こういうことは私も十分わかっているつもりでございます。しかしその一方で、今日本の民意が大きく高度化、多様化している、この点に対する配慮も必要なのではないかなと、このように考えております。
　図を続けて二枚ごらんください。まず最初の図が、異党派投票の現状がどうなっているか、そちらのお手元にもある図でございますが、これは過去二回、平成元年の参議院選挙それから平成四年の参議院選挙におきまして、自民党と社会党におきまして、選挙区選挙と比例代表選挙でどのような投票行動を行っているか、皆さんも御存じの点であると思います。
　これを見ますと、例えば平成元年の参議院選挙におきましては、社会党で、選挙区選挙と比例代表で八・六七ポイントの異党派投票が出ております。平成四年の選挙におきましては、自民党におきまして、選挙区選挙と比例代表選挙で一〇％以上の異党派投票が現実として起こっているわけでございます。これを、自民党、社会党だけではなくて、全政党に広げてみますと、次の図になってまいります。
　これは平成四年の参議院選挙をベースにした試算でございますが、全体で四千五百万投票者の方の中で、選挙区選挙と比例代表選挙で異なる投票行動をされている方が全体の二六・九五％、四人に一人以上いらっしゃいます。そして、選挙区選挙で無所属の候補もしくは連合の会へ入れた方が二〇％近く、それから比例区のみの政党に入れた人が一〇％以上いるわけです。この中でのダブルカウント分を最大限修正いたしましても、異党派投票を行っている人は少なくとも二八・七七％いるわけでございます。言い方を変えますと、同じ政党、同じ政党の候補者に入れる人に対しまして、言ってみれば半分しか投票行動が自由にならない、このような人が三割近くいるわけでございます。
　この異党派投票について、この現状が二％、三％であるなら私も質問はいたしません。しかし、三割近くの人が現実問題として異党派投票を行っているわけでございます。この中で、政党本位、政策本位、こういうお言葉もわかりますが、この現状、三割近くの人がこういう選択をしている、これが今日本の高度化した、多様化した民意なんです。この現状をどのようにごらんになられるか、御質問さしていただきたいと思います。</speech><startPage>32</startPage><speechURL>https://kokkai.ndl.go.jp/txt/112804573X00419931019/209</speechURL><meetingURL>https://kokkai.ndl.go.jp/txt/112804573X00419931019</meetingURL><pdfURL>https://kokkai.ndl.go.jp/img/112804573X00419931019/32</pdfURL></speechRecord></recordData></record><record><recordData><speechRecord><speechID>112804573X00419931019_211</speechID><issueID>112804573X00419931019</issueID><imageKind>会議録</imageKind><searchObject>211</searchObject><session>128</session><nameOfHouse>衆議院</nameOfHouse><nameOfMeeting>政治改革に関する調査特別委員会</nameOfMeeting><issue>第4号</issue><date>1993-10-19</date><closing></closing><speechOrder>211</speechOrder><speaker>茂木敏充</speaker><speakerYomi>もてぎとしみつ</speakerYomi><speakerGroup>さきがけ・日本新党</speakerGroup><speakerPosition></speakerPosition><speakerRole></speakerRole><speech>○茂木委員　私の言葉が足りなかったのかもしれないのですが、将来方向として、向かうべき方向として、政党中心、それから政策中心ということは全く同意見でございます。しかし、現実にこういう状況がある。三割近くの人が異党派投票をしている。それから、将来方向に向かう中で、急に一票制でよろしいのですかと。まず二票制という形で、今の現実も踏まえながらその将来を考えないととても、日本の現実、政治の現実があるわけです。アメリカとも違う、イギリスとも違う、韓国とも違う政治の現実を全く無視して一票制に飛び込んでよろしいのでしょうか、このようなことを御質問申し上げているわけです。</speech><startPage>32</startPage><speechURL>https://kokkai.ndl.go.jp/txt/112804573X00419931019/211</speechURL><meetingURL>https://kokkai.ndl.go.jp/txt/112804573X00419931019</meetingURL><pdfURL>https://kokkai.ndl.go.jp/img/112804573X00419931019/32</pdfURL></speechRecord></recordData></record><record><recordData><speechRecord><speechID>112804573X00419931019_213</speechID><issueID>112804573X00419931019</issueID><imageKind>会議録</imageKind><searchObject>213</searchObject><session>128</session><nameOfHouse>衆議院</nameOfHouse><nameOfMeeting>政治改革に関する調査特別委員会</nameOfMeeting><issue>第4号</issue><date>1993-10-19</date><closing></closing><speechOrder>213</speechOrder><speaker>茂木敏充</speaker><speakerYomi>もてぎとしみつ</speakerYomi><speakerGroup>さきがけ・日本新党</speakerGroup><speakerPosition></speakerPosition><speakerRole></speakerRole><speech>○茂木委員　正直に申し上げます。
　まだ東京都の現状については私なりに試算しておりませんので、もし必要でしたら早急に試算をさせていただきますが、少なくとも衆議院におきましては、このような形の比例が導入されていないという前提で、私は、平成元年度と平成四年度の参議院の結果をベースにしながら議論させていただくということに対しては何らの戸惑いもございません。その上でまた議論させていただければと、このように考えております。
　時間の関係で、次の質問と申しますかまとめの方にそろそろ入らさせていただきたいと思うのですが、きょう、高度化そして多様化した民意を新しい選挙制度のもとでどう生かしていくかにつきまして、私といたしましては三つの観点、すなわち一票の格差、これが二・九七にまでなってくる、こういうポイントから、そして死に票の割合、これが二割近く、一八・七％一つの政党でも出てしまう、そして最後に一票制による投票の制約、これがやはり二八％以上、三割近くに及ぶ、こういう観点から質問をさせていただきました。
　これら三点をまとめさせていただきますと、次のような表になってまいります。
　「総括表」という形でまとめてございますが、「一票の格差」「死票の割合」それから「投票の制約」、この問題につきまして、小選挙区、比例代表、その加重平均、さらに「死票の割合」「一票制による投票の制約」、こういう形でまとめてございます。当然、まだ小選挙区の区割り案が決まってございません。ここでは仮定として、二倍、一・六六倍と、二百五十の場合と三百の場合で三百の方が少なくなってくるのではないかなと、こういう前提を置かさせていただいております。
　実際、けさの読売新聞を見てみましても、こちらの二百五十の方が二・四五、それから三百の方が二・一七。これは相対的に見ますと、逆に私の案では自民党案の方が有利にといいますか格差が少なくなるように出してございます。
　それから、「一政党最大の死票の割合」というのは、これを政党全体でどれだけになるか。これは実際の選挙がありませんとわかりませんが、私もいろいろな試算をこの表をベースにしてみましたが、それぞれの案の相対的な数字の序列、位置関係は、全くどうやっても変わってまいりません。
　これを一つのグラフに落としてみますと、次のようなグラフになってまいります。
　これは縦軸に「一票の格差」をとっております。上に行くほど格差が大きくなるわけです。横軸の方に「死票の割合及び一票制による投票の制約」、右に行くほど制約が大きくなる、このような形でとってございます。一番右上にありますのが自民党案、そして左下にありますのが政府案、このような形になってきます。
　二票制によりまして、ブロック制をとりますと多分この位置あたり、政府案よりちょっと右上がりのあたり、それから二票制で比例区を全国にいたしまして、それからその中で比例区と小選挙区の定数を変えてみますと、これはそれぞれの配分の仕方によって政府案に近い部分になってきます。いずれにいたしましても、政府案と自民案にこれだけの格差が生まれてくるわけでございます。
　今、世界も日本も大きく変化しようとしております。そこの中で、日本の民意も大きく高度化そして多様化しているわけでございます。そんな中で、民意を本当に機敏に新しく集約していこう、こういう考えはわかります。しかし、その一方で、その民意というものをできる限り格差のない形で、制約のない形で、その一票が生きる形で新しい制度のもとで運用していこう、これは本当に党派を超えまして国会議員全員として取り組んでいかなくてはならない問題ではないかな、このように私、新人議員でございますが、考えております。
　自民党案の提案者の方にぜひお伺いしたいのですが、この格差を、そしてこの制約をどのようにごらんになっていらっしゃるか、そしてこの格差、この制約に対して修正の御用意はあられるか、かつて政権党であられた自民党の大きな許容力を今でもお持ちかどうか、お尋ねしたいと思います。</speech><startPage>32</startPage><speechURL>https://kokkai.ndl.go.jp/txt/112804573X00419931019/213</speechURL><meetingURL>https://kokkai.ndl.go.jp/txt/112804573X00419931019</meetingURL><pdfURL>https://kokkai.ndl.go.jp/img/112804573X00419931019/32</pdfURL></speechRecord></recordData></record><record><recordData><speechRecord><speechID>112804573X00419931019_215</speechID><issueID>112804573X00419931019</issueID><imageKind>会議録</imageKind><searchObject>215</searchObject><session>128</session><nameOfHouse>衆議院</nameOfHouse><nameOfMeeting>政治改革に関する調査特別委員会</nameOfMeeting><issue>第4号</issue><date>1993-10-19</date><closing></closing><speechOrder>215</speechOrder><speaker>茂木敏充</speaker><speakerYomi>もてぎとしみつ</speakerYomi><speakerGroup>さきがけ・日本新党</speakerGroup><speakerPosition></speakerPosition><speakerRole></speakerRole><speech>○茂木委員　私は、自民党案と政府提案、ミルクと紅茶だと思っております。どこかで一緒になって、一番ブレンドされた形のいい味が出ればと、このように考えております。
　哲学の問題も重要ですが、同時に、あの問題というのは、先ほど示した問題というのは、必ずしも直線ではございません。両方の歩み寄りによりまして必ず数値的にもいい案がつくれるのではないかなと、このように考えております。
　まだ委員長の方からタイムアップという御指摘はございませんが、私がロンドンで買いました安い時計、これは狂わないんですけれども、これによりますと、我々さきがけ日本新党の方がいただきました質疑時間の一時間が終わろうとしているところでございます。新人議員といたしまして、これからもタイムスケジュールを守った審議というのに努めてまいろうと思っております。
　自民党の先輩議員の皆さん、委員の皆さんにもタイムスケジュールに沿った審議、そして最終的には歩み寄るところは歩み寄って、合意、採決をお願いいたしまして、私の質問を終わらさせていただきます。</speech><startPage>33</startPage><speechURL>https://kokkai.ndl.go.jp/txt/112804573X00419931019/215</speechURL><meetingURL>https://kokkai.ndl.go.jp/txt/112804573X00419931019</meetingURL><pdfURL>https://kokkai.ndl.go.jp/img/112804573X00419931019/33</pdfURL></speechRecord></recordData></record></records></data>
